gtfs_guru/__init__.py
gtfs_guru/gtfs_guru.abi3.so
gtfs_guru-0.1.1.dist-info/METADATA
gtfs_guru-0.1.1.dist-info/WHEEL
gtfs_guru-0.1.1.dist-info/RECORD
