Metadata-Version: 2.4
Name: gtfs-guru
Version: 0.1.1
Classifier: Development Status :: 4 - Beta
Classifier: Intended Audience :: Developers
Classifier: License :: OSI Approved :: Apache Software License
Classifier: Programming Language :: Python :: 3
Classifier: Programming Language :: Python :: 3.8
Classifier: Programming Language :: Python :: 3.9
Classifier: Programming Language :: Python :: 3.10
Classifier: Programming Language :: Python :: 3.11
Classifier: Programming Language :: Python :: 3.12
Classifier: Programming Language :: Rust
Classifier: Topic :: Scientific/Engineering :: GIS
Summary: Fast GTFS validator written in Rust
Keywords: gtfs,transit,validator,public-transit
Home-Page: https://github.com/abasis-ltd/gtfs.guru
License: Apache-2.0
Requires-Python: >=3.8
Project-URL: Homepage, https://github.com/abasis-ltd/gtfs.guru
Project-URL: Repository, https://github.com/abasis-ltd/gtfs.guru
